processamento_imagens_com_python/__init__.py
processamento_imagens_com_python/processing/__init__.py
processamento_imagens_com_python/processing/combination.py
processamento_imagens_com_python/processing/transformation.py
processamento_imagens_com_python/utils/__init__.py
processamento_imagens_com_python/utils/io.py
processamento_imagens_com_python/utils/plot.py
processamento_imagens_com_python-0.0.1.dist-info/METADATA
processamento_imagens_com_python-0.0.1.dist-info/WHEEL
processamento_imagens_com_python-0.0.1.dist-info/top_level.txt
processamento_imagens_com_python-0.0.1.dist-info/RECORD
