Metadata-Version: 2.4
Name: processamento_imagens_com_python
Version: 0.0.1
Summary: Processamento de imagens com Python
Home-page: https://github.com/OsnyNeto/Programas_Python/tree/main/package-template-master
Author: Osny
Author-email: osnynt@gmail.com
Requires-Python: >=3.8
Requires-Dist: matplotlib
Requires-Dist: numpy
Requires-Dist: scikit-image>=0.16.1
Dynamic: author
Dynamic: author-email
Dynamic: description
Dynamic: description-content-type
Dynamic: home-page
Dynamic: requires-dist
Dynamic: requires-python
Dynamic: summary
